TheRuffianReport/HTMLTestRunner.py
TheRuffianReport/__init__.py
TheRuffianReport-1.0.1.dist-info/LICENSE
TheRuffianReport-1.0.1.dist-info/METADATA
TheRuffianReport-1.0.1.dist-info/WHEEL
TheRuffianReport-1.0.1.dist-info/top_level.txt
TheRuffianReport-1.0.1.dist-info/RECORD
