Metadata-Version: 2.1
Name: TheRuffianReport
Version: 1.0.1
Summary: Report for unittest
Home-page: https://github.com/the-ruffian/TheRuffianReport
Download-URL: https://codeload.github.com/the-ruffian/TheRuffianReport/zip/refs/heads/master
Author: TheRuffian
Author-email: TheRuffian <bugpz2779@gmail.com>
License: MIT License
Project-URL: Homepage, https://github.com/the-ruffian/TheRuffianReport
Project-URL: download_page, https://codeload.github.com/the-ruffian/TheRuffianReport/zip/refs/heads/master
Keywords: the-ruffian,ruffianTest,ruffian,TheRuffian,TheRuffianReport
Platform: all
Classifier: Intended Audience :: Developers
Classifier: Operating System :: OS Independent
Classifier: Natural Language :: Chinese (Simplified)
Classifier: Programming Language :: Python :: 3
Classifier: Topic :: Software Development :: Testing
Classifier: Development Status :: 5 - Production/Stable
Classifier: License :: OSI Approved :: MIT License
Requires-Python: >=3.6
License-File: LICENSE
Requires-Dist: requests
